pycovid/__init__.py
pycovid/pycovid.py
pycovid-1.0.0.dist-info/LICENSE
pycovid-1.0.0.dist-info/METADATA
pycovid-1.0.0.dist-info/WHEEL
pycovid-1.0.0.dist-info/top_level.txt
pycovid-1.0.0.dist-info/RECORD
