Metadata-Version: 2.1
Name: pycovid
Version: 1.0.0
Summary: Useful tool to access Rami Krispin Novel Corona Dataset
Home-page: https://github.com/sudharshan-ashok/pycovid
Author: Sudharshan Ashok
Author-email: sudharshan93@gmail.com
License: MIT
Download-URL: https://sudharshan-ashok.github.io
Keywords: Coronavirus,COVID
Platform: UNKNOWN
Requires-Dist: pandas
Requires-Dist: numpy
Requires-Dist: plotly
